django_impersonator-0.0.3.dist-info/licenses/LICENSE
"impersonate/__init__,py"
impersonate/admin.py
impersonate/middleware.py
impersonate/templates/impersonate/popup.html
django_impersonator-0.0.3.dist-info/METADATA
django_impersonator-0.0.3.dist-info/WHEEL
django_impersonator-0.0.3.dist-info/top_level.txt
django_impersonator-0.0.3.dist-info/RECORD
